[
    {
        "client_msg_id": "ce35141d-1d66-423a-b7d8-2806a3df9ca1",
        "type": "message",
        "text": "good morning <!channel> please ignore the invitation from Madini - and attend our class at 9am as usual",
        "user": "U021UNQGZC4",
        "ts": "1623048148.000800",
        "team": "T021KE79B9B",
        "user_team": "T021KE79B9B",
        "source_team": "T021KE79B9B",
        "user_profile": {
            "avatar_hash": "f30ef9a9abe2",
            "image_72": "https:\/\/avatars.slack-edge.com\/2021-05-12\/2049849835622_f30ef9a9abe22ef41bee_72.jpg",
            "first_name": "Sian",
            "real_name": "Sian Davies",
            "display_name": "Sian Davies",
            "team": "T021KE79B9B",
            "name": "sian.davies",
            "is_restricted": false,
            "is_ultra_restricted": false
        },
        "blocks": [
            {
                "type": "rich_text",
                "block_id": "k7RC",
                "elements": [
                    {
                        "type": "rich_text_section",
                        "elements": [
                            {
                                "type": "text",
                                "text": "good morning "
                            },
                            {
                                "type": "broadcast",
                                "range": "channel"
                            },
                            {
                                "type": "text",
                                "text": " please ignore the invitation from Madini - and attend our class at 9am as usual"
                            }
                        ]
                    }
                ]
            }
        ]
    },
    {
        "client_msg_id": "8860a9eb-5379-44ec-93a0-93cfa7629dbe",
        "type": "message",
        "text": "thanks",
        "user": "U021CE3UWPR",
        "ts": "1623048475.001000",
        "team": "T021KE79B9B",
        "user_team": "T021KE79B9B",
        "source_team": "T021KE79B9B",
        "user_profile": {
            "avatar_hash": "02dd48f79a61",
            "image_72": "https:\/\/avatars.slack-edge.com\/2021-05-13\/2058368190389_02dd48f79a614b8d8abf_72.jpg",
            "first_name": "",
            "real_name": "Hector Santos",
            "display_name": "Hector Santos",
            "team": "T021KE79B9B",
            "name": "hectors78",
            "is_restricted": false,
            "is_ultra_restricted": false
        },
        "blocks": [
            {
                "type": "rich_text",
                "block_id": "kZxv",
                "elements": [
                    {
                        "type": "rich_text_section",
                        "elements": [
                            {
                                "type": "text",
                                "text": "thanks"
                            }
                        ]
                    }
                ]
            }
        ]
    }
]